markdown_parser/__init__.py
markdown_parser/node.py
markdown_parser/tree.py
markdown_parser_py-1.0.1.dist-info/licenses/LICENSE
markdown_parser_py-1.0.1.dist-info/METADATA
markdown_parser_py-1.0.1.dist-info/WHEEL
markdown_parser_py-1.0.1.dist-info/top_level.txt
markdown_parser_py-1.0.1.dist-info/RECORD
