Metadata-Version: 2.4
Name: markdown-parser-py
Version: 1.0.1
Summary: Parse, Manipulate, and Merge Markdown Heading Trees Programmatically.
Author-email: Varun Gumma <varun230999@gmail.com>
License: MIT
Project-URL: Homepage, https://github.com/VarunGumma/markdown-parser-py
Project-URL: Repository, https://github.com/VarunGumma/markdown-parser-py
Project-URL: Issues, https://github.com/VarunGumma/markdown-parser-py/issues
Keywords: markdown,parser,tree,document
Classifier: Programming Language :: Python :: 3
Classifier: License :: OSI Approved :: MIT License
Classifier: Operating System :: OS Independent
Requires-Python: >=3.10
License-File: LICENSE
Requires-Dist: regex>=2024.4.16
Dynamic: license-file
